{
  "08130009": {
    "name": "Nevado Chillan",
    "elevation": 2610.0,
    "years": [
      2016,
      2017,
      2018,
      2019,
      2020,
      2021,
      2022,
      2023,
      2024
    ],
    "values": [
      null,
      null,
      null,
      null,
      null,
      null,
      null,
      null,
      null
    ]
  },
  "08374001": {
    "name": "Volcan Chillan",
    "elevation": 2393.0,
    "years": [
      2016,
      2017,
      2018,
      2019,
      2020,
      2021,
      2022,
      2023,
      2024
    ],
    "values": [
      7.6,
      53.3,
      53.2,
      42.6,
      143.1,
      5.4,
      246.6,
      234.3,
      null
    ]
  }
}